{
  "2008": {
    "playerName": "v kohli",
    "strikeRate": 105.096
  },
  "2009": {
    "playerName": "v kohli",
    "strikeRate": 112.329
  },
  "2010": {
    "playerName": "v kohli",
    "strikeRate": 144.811
  },
  "2011": {
    "playerName": "v kohli",
    "strikeRate": 121.087
  },
  "2012": {
    "playerName": "v kohli",
    "strikeRate": 111.656
  },
  "2013": {
    "playerName": "v kohli",
    "strikeRate": 139.216
  },
  "2014": {
    "playerName": "v kohli",
    "strikeRate": 122.109
  },
  "2015": {
    "playerName": "v kohli",
    "strikeRate": 130.829
  },
  "2016": {
    "playerName": "v kohli",
    "strikeRate": 152.031
  },
  "2017": {
    "playerName": "v kohli",
    "strikeRate": 122.222
  }
}